azure_saving/__init__.py
tests/__init__.py
azure_saving-0.0.1.dist-info/LICENSE
azure_saving-0.0.1.dist-info/METADATA
azure_saving-0.0.1.dist-info/WHEEL
azure_saving-0.0.1.dist-info/top_level.txt
azure_saving-0.0.1.dist-info/RECORD
