Metadata-Version: 2.1
Name: azure-saving
Version: 0.0.1
Summary: Azure saving Python package
Home-page: https://azure-saving.readthedocs.io/
Author: Alessandra Bilardi
Author-email: alessandra.bilardi@gmail.com
License: UNKNOWN
Project-URL: Source, https://github.com/bilardi/azure-saving
Project-URL: Bug Reports, https://github.com/bilardi/azure-saving/issues
Project-URL: Funding, https://donate.pypi.org
Platform: UNKNOWN
Classifier: Programming Language :: Python :: 3
Classifier: License :: OSI Approved :: MIT License
Classifier: Operating System :: OS Independent
Requires-Python: >=3.6
